memecrypt/__init__.py
memecrypt/__main__.py
memecrypt/memecrypt.py
memecrypt/terminal_colors.py
memecrypt/utilities.py
memecrypt-1.5.0.dist-info/entry_points.txt
memecrypt-1.5.0.dist-info/LICENSE
memecrypt-1.5.0.dist-info/WHEEL
memecrypt-1.5.0.dist-info/METADATA
memecrypt-1.5.0.dist-info/RECORD
