Metadata-Version: 2.1
Name: memecrypt
Version: 1.5.0
Summary: An encryption tool, designed for CTF challenges and fun purposes.
Home-page: https://github.com/Sh3llcod3/Memecrypt
License: MIT
Author: Sh3llcod3
Author-email: 28938427+Sh3llcod3@users.noreply.github.com
Requires-Python: >=3.6,<4.0
Classifier: License :: OSI Approved :: MIT License
Classifier: Programming Language :: Python :: 3
Classifier: Programming Language :: Python :: 3.6
Classifier: Programming Language :: Python :: 3.7
Classifier: Programming Language :: Python :: 3.8
Classifier: Programming Language :: Python :: 3.9
Requires-Dist: easyparse
Requires-Dist: requests
Project-URL: Repository, https://github.com/Sh3llcod3/Memecrypt
